fedmed/__init__.py
fedmed/core/__init__.py
fedmed/core/data.py
fedmed/core/local.py
fedmed/core/remote.py
fedmed/core/server.py
fedmed/core/simulation.py
fedmed/core/templates.py
fedmed/ops/__init__.py
fedmed/ops/binary.py
fedmed/ops/private.py
fedmed/ops/public.py
fedmed/privacy/__init__.py
fedmed/privacy/anonymity.py
fedmed/privacy/coarsening.py
fedmed/privacy/combined.py
fedmed/privacy/memory.py
fedmed/privacy/noise.py
fedmed/privacy/saturation.py
fedmed/privacy/trustful.py
fedmed/stats/__init__.py
fedmed/stats/base.py
fedmed/stats/correlation.py
fedmed/stats/test.py
FedMed-0.3.2.dist-info/METADATA
FedMed-0.3.2.dist-info/WHEEL
FedMed-0.3.2.dist-info/top_level.txt
FedMed-0.3.2.dist-info/RECORD
