Metadata-Version: 2.1
Name: FedMed
Version: 0.3.2
Summary: A privacy-aware federated computing library to let non-trusted clients perform statistical analysis.
Home-page: https://github.com/maniospas/FedMed
Author: Emmanouil (Manios) Krasanakis
Author-email: maniospas@hotmail.com
Classifier: Programming Language :: Python :: 3
Classifier: License :: OSI Approved :: Apache Software License
Classifier: Operating System :: OS Independent
Requires-Dist: numpy
Requires-Dist: pyyaml
Requires-Dist: flask
Requires-Dist: waitress
Requires-Dist: matplotlib
Requires-Dist: psutil
